Bala/__init__.py
Bala/__main__.py
Bala/print_me_func.py
bala-0.1.0.dist-info/licenses/LICENSE.txt
bala-0.1.0.dist-info/METADATA
bala-0.1.0.dist-info/WHEEL
bala-0.1.0.dist-info/entry_points.txt
bala-0.1.0.dist-info/top_level.txt
bala-0.1.0.dist-info/RECORD
