Metadata-Version: 2.4
Name: Bala
Version: 0.1.0
Summary: My first package!
Author-email: Bala <Bala@gmail.com>
Maintainer-email: Bala <Bala@gmail.com>
License: Copyright 2025 Bala
Project-URL: Homepage, https://github.com/jfuruness/justin_furuness
Project-URL: Documentation, https://github.com/jfuruness/justin_furuness/README.md
Keywords: Furuness
Classifier: Programming Language :: Python :: 3.9
Classifier: Programming Language :: Python :: Implementation :: CPython
Classifier: License :: OSI Approved :: BSD License
Classifier: Intended Audience :: Developers
Classifier: Operating System :: POSIX :: Linux
Classifier: Operating System :: Microsoft :: Windows
Classifier: Operating System :: MacOS
Classifier: Operating System :: MacOS :: MacOS X
Requires-Python: >=3.9
License-File: LICENSE.txt
Dynamic: license-file
